Annoroad_OMIC_vis-1.0.3.dist-info/METADATA
Annoroad_OMIC_vis-1.0.3.dist-info/RECORD
Annoroad_OMIC_vis-1.0.3.dist-info/WHEEL
Annoroad_OMIC_vis-1.0.3.dist-info/entry_points.txt
Annoroad_OMIC_vis-1.0.3.dist-info/top_level.txt
Annoroad_vis/__init__.py
Annoroad_vis/main.py
