Metadata-Version: 2.1
Name: Annoroad-OMIC-vis
Version: 1.0.3
Summary: Hi-C OMIC display tools
Home-page: UNKNOWN
Author: Zhao Yue
Author-email: zhao_yue000@163.com
License: UNKNOWN
Platform: UNKNOWN
